cmbook.py
cmbook-1.0.dist-info/WHEEL
cmbook-1.0.dist-info/METADATA
cmbook-1.0.dist-info/RECORD
