Metadata-Version: 2.1
Name: cmbook
Version: 1.0
Summary: CoolMemory-English 是一个免费的记单词软件，它在传统的记单词方式（听、说、读、写）之外提供了一种新的方式：敲
Keywords: 英语,单词,English,CoolMemory-English,cmbook,翻译,背单词
Author-email: "lcctoor.com" <lcctoor@outlook.com>
Project-URL: HomePage, https://lcctoor.github.io/works/CoolMemory-English
